tabular_data_synthesizer/__init__.py
tabular_data_synthesizer/constants.py
tabular_data_synthesizer/ctgan.py
tabular_data_synthesizer/nonlinearity.py
tabular_data_synthesizer/optimizers.py
tabular_data_synthesizer/preprocessor.py
Tabular_Data_Synthesizer-0.1.dist-info/METADATA
Tabular_Data_Synthesizer-0.1.dist-info/WHEEL
Tabular_Data_Synthesizer-0.1.dist-info/top_level.txt
Tabular_Data_Synthesizer-0.1.dist-info/RECORD
