Metadata-Version: 2.1
Name: Tabular-Data-Synthesizer
Version: 0.1
Summary: A package to evaluate how close a synthetic data set is to real data.
Home-page: https://github.com/Baukebrenninkmeijer/Tabular-data-synthesizer
Author: Bauke Brenninkmeijer
Author-email: bauke.brenninkmeijer@gmail.com
License: UNKNOWN
Keywords: SYNTHETIC-DATA,GANs,SAMPLING,FAKE-DATA,TEST-DATA
Platform: UNKNOWN
Classifier: Programming Language :: Python :: 3
Classifier: License :: OSI Approved :: MIT License
Classifier: Operating System :: OS Independent
Requires-Dist: pandas
Requires-Dist: numpy
Requires-Dist: sdgym
Requires-Dist: tqdm
Requires-Dist: psutil
